vidbcontrol/CSQL.py
vidbcontrol/DBCallBack.py
vidbcontrol/DBConn.py
vidbcontrol/Error.py
vidbcontrol/__init__.py
vidbcontrol/py.typed
vidbcontrol-0.1.0.dist-info/METADATA
vidbcontrol-0.1.0.dist-info/WHEEL
vidbcontrol-0.1.0.dist-info/licenses/LICENSE.txt
vidbcontrol-0.1.0.dist-info/RECORD
