Metadata-Version: 2.4
Name: vidbcontrol
Version: 0.1.0
Summary: Add your description here
License-File: LICENSE.txt
Requires-Python: >=3.10
Requires-Dist: psycopg2>=2.9.10
